streamlit_player/__init__.py
streamlit_player/frontend/build/asset-manifest.json
streamlit_player/frontend/build/bootstrap.min.css
streamlit_player/frontend/build/index.html
streamlit_player/frontend/build/precache-manifest.0113dc9dfceece46fd9d3a8425442c91.js
streamlit_player/frontend/build/precache-manifest.44a99eca37f627ea479312bf0a57ba93.js
streamlit_player/frontend/build/precache-manifest.50cd646fc86e2c71d5105380cf085de9.js
streamlit_player/frontend/build/precache-manifest.9cdc64becbdfe21cf2ff476261913b5a.js
streamlit_player/frontend/build/precache-manifest.ecbbb2f2c95119d05ca9cc2cdee30a00.js
streamlit_player/frontend/build/service-worker.js
streamlit_player/frontend/build/static/js/2.361cb7a0.chunk.js
streamlit_player/frontend/build/static/js/2.361cb7a0.chunk.js.LICENSE.txt
streamlit_player/frontend/build/static/js/2.361cb7a0.chunk.js.map
streamlit_player/frontend/build/static/js/2.5758de74.chunk.js
streamlit_player/frontend/build/static/js/2.5758de74.chunk.js.LICENSE.txt
streamlit_player/frontend/build/static/js/2.5758de74.chunk.js.map
streamlit_player/frontend/build/static/js/2.6977e18c.chunk.js
streamlit_player/frontend/build/static/js/2.6977e18c.chunk.js.LICENSE.txt
streamlit_player/frontend/build/static/js/2.6977e18c.chunk.js.map
streamlit_player/frontend/build/static/js/main.0054d9ad.chunk.js
streamlit_player/frontend/build/static/js/main.0054d9ad.chunk.js.map
streamlit_player/frontend/build/static/js/main.2fe15bb3.chunk.js
streamlit_player/frontend/build/static/js/main.2fe15bb3.chunk.js.map
streamlit_player/frontend/build/static/js/main.450b8766.chunk.js
streamlit_player/frontend/build/static/js/main.450b8766.chunk.js.map
streamlit_player/frontend/build/static/js/main.a9063e60.chunk.js
streamlit_player/frontend/build/static/js/main.a9063e60.chunk.js.map
streamlit_player/frontend/build/static/js/main.b7508049.chunk.js
streamlit_player/frontend/build/static/js/main.b7508049.chunk.js.map
streamlit_player/frontend/build/static/js/runtime-main.f7c53578.js
streamlit_player-0.1.5.dist-info/LICENSE
streamlit_player-0.1.5.dist-info/METADATA
streamlit_player-0.1.5.dist-info/WHEEL
streamlit_player-0.1.5.dist-info/top_level.txt
streamlit_player-0.1.5.dist-info/RECORD
