Metadata-Version: 2.1
Name: streamlit-player
Version: 0.1.5
Summary: A streamlit component to embed video and music players from various websites.
Home-page: https://github.com/okld/streamlit-player
Author: okld
Author-email: 
License: UNKNOWN
Platform: UNKNOWN
Requires-Python: >=3.6
